{
  "hoje": {
    "faturamento": 713.97,
    "faturamento_delta": 0,
    "ticket_medio": 9.65,
    "ticket_delta": 0,
    "transacoes": 74,
    "transacoes_delta": 0,
    "margem_media": 0,
    "margem_delta": 0,
    "por_hora": [
      18,
      0,
      0,
      2,
      1,
      0,
      1,
      0,
      10,
      2,
      7,
      5,
      10,
      6,
      3,
      5,
      1,
      3,
      0,
      0,
      0,
      0,
      0,
      0
    ],
    "por_hora_soul": [
      16,
      0,
      0,
      2,
      1,
      0,
      1,
      0,
      10,
      2,
      7,
      5,
      10,
      5,
      3,
      5,
      1,
      1,
      0,
      0,
      0,
      0,
      0,
      0
    ],
    "por_hora_mini": [
      2,
      0,
      0,
      0,
      0,
      0,
      0,
      0,
      0,
      0,
      0,
      0,
      0,
      1,
      0,
      0,
      0,
      2,
      0,
      0,
      0,
      0,
      0,
      0
    ],
    "top_produtos": [
      {
        "nome": "HEINEKEN CERVEJA PURO MALTE COM ÁLCOOL-350ML",
        "vendas": 5,
        "receita": 39.95,
        "margem": 0
      },
      {
        "nome": "NISSIN LÁMEN MACARRÃO INSTANTÂNEO COM TEMPERO SABOR GALINHA CAIPIRA-80G",
        "vendas": 4,
        "receita": 19.96,
        "margem": 0
      },
      {
        "nome": "FRESCOA ÁGUA MINERAL NATURAL SEM GÁS-1,5L",
        "vendas": 4,
        "receita": 23.96,
        "margem": 0
      },
      {
        "nome": "COCA-COLA REFRIGERANTE DE SABOR ORIGINAL-600ML",
        "vendas": 3,
        "receita": 23.97,
        "margem": 0
      },
      {
        "nome": "BOLO DE POTE-BRIGADEIRO-250G",
        "vendas": 3,
        "receita": 50.97,
        "margem": 0
      },
      {
        "nome": "HALLS BALA DURA SABOR ARTIFICIAL DE CEREJA-28g",
        "vendas": 2,
        "receita": 7.18,
        "margem": 0
      },
      {
        "nome": "COCA-COLA REFRIGERANTE ZERO AÇÚCAR -2L",
        "vendas": 2,
        "receita": 29.98,
        "margem": 0
      },
      {
        "nome": "KIBON ESK SORV M BBOM 92,1G",
        "vendas": 2,
        "receita": 43.98,
        "margem": 0
      },
      {
        "nome": "CRYSTAL  ÁGUA MIN S GÁS-500ML",
        "vendas": 2,
        "receita": 7.98,
        "margem": 0
      },
      {
        "nome": "SANDUÍCHE CREMOSO FRANGO",
        "vendas": 2,
        "receita": 25.98,
        "margem": 0
      }
    ],
    "analise_margem": [
      {
        "nome": "BOLO DE POTE-BRIGADEIRO-250G",
        "margem": 100,
        "tem_custo": false,
        "giro": 3,
        "receita": 50.97,
        "lucro": 50.97,
        "hora_pico": "0h",
        "classificacao": "volume",
        "cls_label": "📦 Alto giro"
      },
      {
        "nome": "KIBON ESK SORV M BBOM 92,1G",
        "margem": 100,
        "tem_custo": false,
        "giro": 2,
        "receita": 43.98,
        "lucro": 43.98,
        "hora_pico": "0h",
        "classificacao": "volume",
        "cls_label": "📦 Alto giro"
      },
      {
        "nome": "HEINEKEN CERVEJA PURO MALTE COM ÁLCOOL-350ML",
        "margem": 100,
        "tem_custo": false,
        "giro": 5,
        "receita": 39.95,
        "lucro": 39.95,
        "hora_pico": "10h",
        "classificacao": "volume",
        "cls_label": "📦 Alto giro"
      },
      {
        "nome": "DURACELL AA 4 DURA 10XMÁS/MAIS-CONTÉM 4 UNIDADES",
        "margem": 100,
        "tem_custo": false,
        "giro": 1,
        "receita": 35.99,
        "lucro": 35.99,
        "hora_pico": "13h",
        "classificacao": "volume",
        "cls_label": "📦 Alto giro"
      },
      {
        "nome": "COCA-COLA REFRIGERANTE ZERO AÇÚCAR -2L",
        "margem": 100,
        "tem_custo": false,
        "giro": 2,
        "receita": 29.98,
        "lucro": 29.98,
        "hora_pico": "14h",
        "classificacao": "volume",
        "cls_label": "📦 Alto giro"
      },
      {
        "nome": "SANDUÍCHE CREMOSO FRANGO",
        "margem": 100,
        "tem_custo": false,
        "giro": 2,
        "receita": 25.98,
        "lucro": 25.98,
        "hora_pico": "10h",
        "classificacao": "volume",
        "cls_label": "📦 Alto giro"
      },
      {
        "nome": "COCA-COLA REFRIGERANTE DE SABOR ORIGINAL-600ML",
        "margem": 100,
        "tem_custo": false,
        "giro": 3,
        "receita": 23.97,
        "lucro": 23.97,
        "hora_pico": "0h",
        "classificacao": "volume",
        "cls_label": "📦 Alto giro"
      },
      {
        "nome": "FRESCOA ÁGUA MINERAL NATURAL SEM GÁS-1,5L",
        "margem": 100,
        "tem_custo": false,
        "giro": 4,
        "receita": 23.96,
        "lucro": 23.96,
        "hora_pico": "15h",
        "classificacao": "volume",
        "cls_label": "📦 Alto giro"
      },
      {
        "nome": "MELITTA CAPPUCCINO TRADICIONAL 200 G",
        "margem": 100,
        "tem_custo": false,
        "giro": 1,
        "receita": 22.59,
        "lucro": 22.59,
        "hora_pico": "10h",
        "classificacao": "volume",
        "cls_label": "📦 Alto giro"
      },
      {
        "nome": "NESTLÉ BEBIDA CREMOSA",
        "margem": 100,
        "tem_custo": false,
        "giro": 2,
        "receita": 19.98,
        "lucro": 19.98,
        "hora_pico": "6h",
        "classificacao": "volume",
        "cls_label": "📦 Alto giro"
      },
      {
        "nome": "NISSIN LÁMEN MACARRÃO INSTANTÂNEO COM TEMPERO SABOR GALINHA CAIPIRA-80G",
        "margem": 100,
        "tem_custo": false,
        "giro": 4,
        "receita": 19.96,
        "lucro": 19.96,
        "hora_pico": "12h",
        "classificacao": "volume",
        "cls_label": "📦 Alto giro"
      },
      {
        "nome": "NEVE PAPEL HIGIÊNICO NEUTRO FOLHA DUPLA-CONTÉM 04 ROLOS",
        "margem": 100,
        "tem_custo": false,
        "giro": 1,
        "receita": 16.99,
        "lucro": 16.99,
        "hora_pico": "13h",
        "classificacao": "volume",
        "cls_label": "📦 Alto giro"
      },
      {
        "nome": "NESTLÉ CAFÉ TORRADO EM GRÃOS",
        "margem": 100,
        "tem_custo": false,
        "giro": 2,
        "receita": 15.98,
        "lucro": 15.98,
        "hora_pico": "8h",
        "classificacao": "volume",
        "cls_label": "📦 Alto giro"
      },
      {
        "nome": "YOKI BATATA PALHA EXTRAFINA-FRITA-100G",
        "margem": 100,
        "tem_custo": false,
        "giro": 1,
        "receita": 14.99,
        "lucro": 14.99,
        "hora_pico": "0h",
        "classificacao": "volume",
        "cls_label": "📦 Alto giro"
      },
      {
        "nome": "WRAP FRANGO",
        "margem": 100,
        "tem_custo": false,
        "giro": 1,
        "receita": 14.99,
        "lucro": 14.99,
        "hora_pico": "4h",
        "classificacao": "volume",
        "cls_label": "📦 Alto giro"
      },
      {
        "nome": "DORITOs 120G",
        "margem": 100,
        "tem_custo": false,
        "giro": 1,
        "receita": 14.99,
        "lucro": 14.99,
        "hora_pico": "0h",
        "classificacao": "volume",
        "cls_label": "📦 Alto giro"
      },
      {
        "nome": "MONSTER ENERGY SEM AÇÚCARES",
        "margem": 100,
        "tem_custo": false,
        "giro": 1,
        "receita": 13.99,
        "lucro": 13.99,
        "hora_pico": "9h",
        "classificacao": "volume",
        "cls_label": "📦 Alto giro"
      },
      {
        "nome": "RED BULL SUGARFREE- 250ML",
        "margem": 100,
        "tem_custo": false,
        "giro": 1,
        "receita": 12.99,
        "lucro": 12.99,
        "hora_pico": "0h",
        "classificacao": "volume",
        "cls_label": "📦 Alto giro"
      },
      {
        "nome": "GUARANÁ REFRIGERANTE DE GUARANÁ ANTARCTICA ORIGINAL-2L",
        "margem": 100,
        "tem_custo": false,
        "giro": 1,
        "receita": 12.99,
        "lucro": 12.99,
        "hora_pico": "3h",
        "classificacao": "volume",
        "cls_label": "📦 Alto giro"
      },
      {
        "nome": "VIGOR REQUEIJAO",
        "margem": 100,
        "tem_custo": false,
        "giro": 1,
        "receita": 12.99,
        "lucro": 12.99,
        "hora_pico": "3h",
        "classificacao": "volume",
        "cls_label": "📦 Alto giro"
      }
    ],
    "estoque_baixo": [],
    "instalacoes": {
      "soul_brooklin": {
        "nome": "Mercadinho 1",
        "faturamento": 682.62,
        "transacoes": 69
      },
      "minimart": {
        "nome": "Mercadinho 2",
        "faturamento": 31.35,
        "transacoes": 5
      }
    }
  },
  "semana": {
    "faturamento": 12519.95,
    "faturamento_delta": 0,
    "ticket_medio": 10.06,
    "ticket_delta": 0,
    "transacoes": 1244,
    "transacoes_delta": 0,
    "margem_media": 0,
    "margem_delta": 0,
    "por_hora": [
      57,
      10,
      17,
      10,
      7,
      1,
      11,
      22,
      50,
      42,
      34,
      43,
      61,
      58,
      53,
      54,
      73,
      70,
      59,
      131,
      104,
      126,
      98,
      53
    ],
    "por_hora_soul": [
      55,
      9,
      17,
      10,
      7,
      1,
      11,
      22,
      49,
      38,
      33,
      39,
      57,
      57,
      50,
      54,
      63,
      66,
      56,
      129,
      103,
      119,
      95,
      51
    ],
    "por_hora_mini": [
      2,
      1,
      0,
      0,
      0,
      0,
      0,
      0,
      1,
      4,
      1,
      4,
      4,
      1,
      3,
      0,
      10,
      4,
      3,
      2,
      1,
      7,
      3,
      2
    ],
    "top_produtos": [
      {
        "nome": "FRESCOA ÁGUA MINERAL NATURAL SEM GÁS-1,5L",
        "vendas": 105,
        "receita": 628.95,
        "margem": 0
      },
      {
        "nome": "HEINEKEN CERVEJA PURO MALTE COM ÁLCOOL-350ML",
        "vendas": 51,
        "receita": 407.49,
        "margem": 0
      },
      {
        "nome": "NESTLÉ BEBIDA CREMOSA",
        "vendas": 50,
        "receita": 499.5,
        "margem": 0
      },
      {
        "nome": "BUDWEISER CERVEJA 330ML",
        "vendas": 38,
        "receita": 265.62,
        "margem": 0
      },
      {
        "nome": "CRYSTAL  ÁGUA MIN C GÁS-500ML",
        "vendas": 37,
        "receita": 147.63,
        "margem": 0
      },
      {
        "nome": "COCA-COLA ZERO 600 ML",
        "vendas": 33,
        "receita": 280.17,
        "margem": 0
      },
      {
        "nome": "NESTLÉ CAFÉ TORRADO EM GRÃOS",
        "vendas": 29,
        "receita": 231.71,
        "margem": 0
      },
      {
        "nome": "COCA-COLA REFRIGERANTE ZERO AÇÚCAR -2L",
        "vendas": 24,
        "receita": 359.76,
        "margem": 0
      },
      {
        "nome": "NISSIN LÁMEN MACARRÃO INSTANTÂNEO COM TEMPERO SABOR GALINHA CAIPIRA-80G",
        "vendas": 20,
        "receita": 99.3,
        "margem": 0
      },
      {
        "nome": "COCA-COLA REFRIGERANTE ZERO AÇÚCAR -350ML",
        "vendas": 20,
        "receita": 119.8,
        "margem": 0
      }
    ],
    "analise_margem": [
      {
        "nome": "FRESCOA ÁGUA MINERAL NATURAL SEM GÁS-1,5L",
        "margem": 100,
        "tem_custo": false,
        "giro": 105,
        "receita": 628.95,
        "lucro": 628.95,
        "hora_pico": "21h",
        "classificacao": "volume",
        "cls_label": "📦 Alto giro"
      },
      {
        "nome": "NESTLÉ BEBIDA CREMOSA",
        "margem": 100,
        "tem_custo": false,
        "giro": 50,
        "receita": 499.5,
        "lucro": 499.5,
        "hora_pico": "8h",
        "classificacao": "volume",
        "cls_label": "📦 Alto giro"
      },
      {
        "nome": "HEINEKEN CERVEJA PURO MALTE COM ÁLCOOL-350ML",
        "margem": 100,
        "tem_custo": false,
        "giro": 51,
        "receita": 407.49,
        "lucro": 407.49,
        "hora_pico": "17h",
        "classificacao": "volume",
        "cls_label": "📦 Alto giro"
      },
      {
        "nome": "COCA-COLA REFRIGERANTE ZERO AÇÚCAR -2L",
        "margem": 100,
        "tem_custo": false,
        "giro": 24,
        "receita": 359.76,
        "lucro": 359.76,
        "hora_pico": "20h",
        "classificacao": "volume",
        "cls_label": "📦 Alto giro"
      },
      {
        "nome": "COCA-COLA ZERO 600 ML",
        "margem": 100,
        "tem_custo": false,
        "giro": 33,
        "receita": 280.17,
        "lucro": 280.17,
        "hora_pico": "21h",
        "classificacao": "volume",
        "cls_label": "📦 Alto giro"
      },
      {
        "nome": "BUDWEISER CERVEJA 330ML",
        "margem": 100,
        "tem_custo": false,
        "giro": 38,
        "receita": 265.62,
        "lucro": 265.62,
        "hora_pico": "19h",
        "classificacao": "volume",
        "cls_label": "📦 Alto giro"
      },
      {
        "nome": "NESTLÉ CAFÉ TORRADO EM GRÃOS",
        "margem": 100,
        "tem_custo": false,
        "giro": 29,
        "receita": 231.71,
        "lucro": 231.71,
        "hora_pico": "8h",
        "classificacao": "volume",
        "cls_label": "📦 Alto giro"
      },
      {
        "nome": "BLUE MOON BELGIAN WHITE-350ML",
        "margem": 100,
        "tem_custo": false,
        "giro": 19,
        "receita": 208.81,
        "lucro": 208.81,
        "hora_pico": "20h",
        "classificacao": "volume",
        "cls_label": "📦 Alto giro"
      },
      {
        "nome": "PÃO DE LEITE",
        "margem": 100,
        "tem_custo": false,
        "giro": 16,
        "receita": 207.84,
        "lucro": 207.84,
        "hora_pico": "0h",
        "classificacao": "volume",
        "cls_label": "📦 Alto giro"
      },
      {
        "nome": "KIBON ESK SORV M BBOM 92,1G",
        "margem": 100,
        "tem_custo": false,
        "giro": 9,
        "receita": 197.91,
        "lucro": 197.91,
        "hora_pico": "0h",
        "classificacao": "volume",
        "cls_label": "📦 Alto giro"
      },
      {
        "nome": "NESTLE CHCO TRIO",
        "margem": 100,
        "tem_custo": false,
        "giro": 11,
        "receita": 153.89,
        "lucro": 153.89,
        "hora_pico": "13h",
        "classificacao": "volume",
        "cls_label": "📦 Alto giro"
      },
      {
        "nome": "CRYSTAL  ÁGUA MIN C GÁS-500ML",
        "margem": 100,
        "tem_custo": false,
        "giro": 37,
        "receita": 147.63,
        "lucro": 147.63,
        "hora_pico": "22h",
        "classificacao": "volume",
        "cls_label": "📦 Alto giro"
      },
      {
        "nome": "SMIRNOFF ICE ORIGINAL BEBIDA MISTA 275ML",
        "margem": 100,
        "tem_custo": false,
        "giro": 14,
        "receita": 146.86,
        "lucro": 146.86,
        "hora_pico": "19h",
        "classificacao": "volume",
        "cls_label": "📦 Alto giro"
      },
      {
        "nome": "STELLA ARTOIS PURE GOLD 330 ML",
        "margem": 100,
        "tem_custo": false,
        "giro": 15,
        "receita": 142.35,
        "lucro": 142.35,
        "hora_pico": "14h",
        "classificacao": "volume",
        "cls_label": "📦 Alto giro"
      },
      {
        "nome": "HEREFORD",
        "margem": 100,
        "tem_custo": false,
        "giro": 2,
        "receita": 139.98,
        "lucro": 139.98,
        "hora_pico": "14h",
        "classificacao": "volume",
        "cls_label": "📦 Alto giro"
      },
      {
        "nome": "COCA-COLA REFRIGERANTE DE SABOR ORIGINAL-600ML",
        "margem": 100,
        "tem_custo": false,
        "giro": 16,
        "receita": 127.84,
        "lucro": 127.84,
        "hora_pico": "21h",
        "classificacao": "volume",
        "cls_label": "📦 Alto giro"
      },
      {
        "nome": "COCA-COLA REFRIGERANTE SABOR ORIGINAL -2L",
        "margem": 100,
        "tem_custo": false,
        "giro": 9,
        "receita": 125.91,
        "lucro": 125.91,
        "hora_pico": "21h",
        "classificacao": "volume",
        "cls_label": "📦 Alto giro"
      },
      {
        "nome": "MONSTER ENERGY SEM AÇÚCARES",
        "margem": 100,
        "tem_custo": false,
        "giro": 9,
        "receita": 125.91,
        "lucro": 125.91,
        "hora_pico": "0h",
        "classificacao": "volume",
        "cls_label": "📦 Alto giro"
      },
      {
        "nome": "ITAMBÉ QUEIJO MUSSARELA FATIADO-150G",
        "margem": 100,
        "tem_custo": false,
        "giro": 8,
        "receita": 119.92,
        "lucro": 119.92,
        "hora_pico": "10h",
        "classificacao": "volume",
        "cls_label": "📦 Alto giro"
      },
      {
        "nome": "COCA-COLA REFRIGERANTE ZERO AÇÚCAR -350ML",
        "margem": 100,
        "tem_custo": false,
        "giro": 20,
        "receita": 119.8,
        "lucro": 119.8,
        "hora_pico": "21h",
        "classificacao": "volume",
        "cls_label": "📦 Alto giro"
      }
    ],
    "estoque_baixo": [],
    "instalacoes": {
      "soul_brooklin": {
        "nome": "Mercadinho 1",
        "faturamento": 12077.77,
        "transacoes": 1191
      },
      "minimart": {
        "nome": "Mercadinho 2",
        "faturamento": 442.18,
        "transacoes": 53
      }
    }
  },
  "mes": {
    "faturamento": 33168.02,
    "faturamento_delta": 0,
    "ticket_medio": 10.1,
    "ticket_delta": 0,
    "transacoes": 3284,
    "transacoes_delta": 0,
    "margem_media": 0,
    "margem_delta": 0,
    "por_hora": [
      109,
      52,
      38,
      29,
      30,
      37,
      41,
      72,
      88,
      93,
      87,
      118,
      151,
      172,
      139,
      153,
      190,
      217,
      242,
      293,
      267,
      295,
      218,
      153
    ],
    "por_hora_soul": [
      104,
      47,
      38,
      29,
      27,
      35,
      39,
      62,
      85,
      83,
      85,
      111,
      141,
      159,
      129,
      133,
      166,
      207,
      235,
      281,
      253,
      283,
      202,
      138
    ],
    "por_hora_mini": [
      5,
      5,
      0,
      0,
      3,
      2,
      2,
      10,
      3,
      10,
      2,
      7,
      10,
      13,
      10,
      20,
      24,
      10,
      7,
      12,
      14,
      12,
      16,
      15
    ],
    "top_produtos": [
      {
        "nome": "FRESCOA ÁGUA MINERAL NATURAL SEM GÁS-1,5L",
        "vendas": 280,
        "receita": 1677.2,
        "margem": 0
      },
      {
        "nome": "HEINEKEN CERVEJA PURO MALTE COM ÁLCOOL-350ML",
        "vendas": 153,
        "receita": 1222.47,
        "margem": 0
      },
      {
        "nome": "NESTLÉ BEBIDA CREMOSA",
        "vendas": 93,
        "receita": 929.07,
        "margem": 0
      },
      {
        "nome": "NESTLÉ CAFÉ TORRADO EM GRÃOS",
        "vendas": 90,
        "receita": 719.1,
        "margem": 0
      },
      {
        "nome": "COCA-COLA ZERO 600 ML",
        "vendas": 87,
        "receita": 738.63,
        "margem": 0
      },
      {
        "nome": "STELLA ARTOIS PURE GOLD 330 ML",
        "vendas": 80,
        "receita": 759.2,
        "margem": 0
      },
      {
        "nome": "BUDWEISER CERVEJA 330ML",
        "vendas": 70,
        "receita": 489.3,
        "margem": 0
      },
      {
        "nome": "CRYSTAL  ÁGUA MIN C GÁS-500ML",
        "vendas": 68,
        "receita": 271.32,
        "margem": 0
      },
      {
        "nome": "COCA-COLA REFRIGERANTE ZERO AÇÚCAR -350ML",
        "vendas": 55,
        "receita": 329.45,
        "margem": 0
      },
      {
        "nome": "COCA-COLA REFRIGERANTE ZERO AÇÚCAR -2L",
        "vendas": 52,
        "receita": 778.85,
        "margem": 0
      }
    ],
    "analise_margem": [
      {
        "nome": "FRESCOA ÁGUA MINERAL NATURAL SEM GÁS-1,5L",
        "margem": 100,
        "tem_custo": false,
        "giro": 280,
        "receita": 1677.2,
        "lucro": 1677.2,
        "hora_pico": "21h",
        "classificacao": "volume",
        "cls_label": "📦 Alto giro"
      },
      {
        "nome": "HEINEKEN CERVEJA PURO MALTE COM ÁLCOOL-350ML",
        "margem": 100,
        "tem_custo": false,
        "giro": 153,
        "receita": 1222.47,
        "lucro": 1222.47,
        "hora_pico": "21h",
        "classificacao": "volume",
        "cls_label": "📦 Alto giro"
      },
      {
        "nome": "NESTLÉ BEBIDA CREMOSA",
        "margem": 100,
        "tem_custo": false,
        "giro": 93,
        "receita": 929.07,
        "lucro": 929.07,
        "hora_pico": "9h",
        "classificacao": "volume",
        "cls_label": "📦 Alto giro"
      },
      {
        "nome": "COCA-COLA REFRIGERANTE ZERO AÇÚCAR -2L",
        "margem": 100,
        "tem_custo": false,
        "giro": 52,
        "receita": 778.85,
        "lucro": 778.85,
        "hora_pico": "20h",
        "classificacao": "volume",
        "cls_label": "📦 Alto giro"
      },
      {
        "nome": "STELLA ARTOIS PURE GOLD 330 ML",
        "margem": 100,
        "tem_custo": false,
        "giro": 80,
        "receita": 759.2,
        "lucro": 759.2,
        "hora_pico": "14h",
        "classificacao": "volume",
        "cls_label": "📦 Alto giro"
      },
      {
        "nome": "COCA-COLA ZERO 600 ML",
        "margem": 100,
        "tem_custo": false,
        "giro": 87,
        "receita": 738.63,
        "lucro": 738.63,
        "hora_pico": "21h",
        "classificacao": "volume",
        "cls_label": "📦 Alto giro"
      },
      {
        "nome": "NESTLÉ CAFÉ TORRADO EM GRÃOS",
        "margem": 100,
        "tem_custo": false,
        "giro": 90,
        "receita": 719.1,
        "lucro": 719.1,
        "hora_pico": "8h",
        "classificacao": "volume",
        "cls_label": "📦 Alto giro"
      },
      {
        "nome": "YOPRO BARRA MORANGO",
        "margem": 100,
        "tem_custo": false,
        "giro": 36,
        "receita": 503.64,
        "lucro": 503.64,
        "hora_pico": "16h",
        "classificacao": "volume",
        "cls_label": "📦 Alto giro"
      },
      {
        "nome": "BUDWEISER CERVEJA 330ML",
        "margem": 100,
        "tem_custo": false,
        "giro": 70,
        "receita": 489.3,
        "lucro": 489.3,
        "hora_pico": "20h",
        "classificacao": "volume",
        "cls_label": "📦 Alto giro"
      },
      {
        "nome": "BLUE MOON BELGIAN WHITE-350ML",
        "margem": 100,
        "tem_custo": false,
        "giro": 44,
        "receita": 483.56,
        "lucro": 483.56,
        "hora_pico": "22h",
        "classificacao": "volume",
        "cls_label": "📦 Alto giro"
      },
      {
        "nome": "KIBON ESK SORV M BBOM 92,1G",
        "margem": 100,
        "tem_custo": false,
        "giro": 20,
        "receita": 439.8,
        "lucro": 439.8,
        "hora_pico": "14h",
        "classificacao": "volume",
        "cls_label": "📦 Alto giro"
      },
      {
        "nome": "PÃO DE LEITE",
        "margem": 100,
        "tem_custo": false,
        "giro": 31,
        "receita": 402.69,
        "lucro": 402.69,
        "hora_pico": "18h",
        "classificacao": "volume",
        "cls_label": "📦 Alto giro"
      },
      {
        "nome": "LAYS SABOR SOUR",
        "margem": 100,
        "tem_custo": false,
        "giro": 28,
        "receita": 391.72,
        "lucro": 391.72,
        "hora_pico": "19h",
        "classificacao": "volume",
        "cls_label": "📦 Alto giro"
      },
      {
        "nome": "SANDUÍCHE BRIOCHE SALAME",
        "margem": 100,
        "tem_custo": false,
        "giro": 26,
        "receita": 363.74,
        "lucro": 363.74,
        "hora_pico": "5h",
        "classificacao": "volume",
        "cls_label": "📦 Alto giro"
      },
      {
        "nome": "SAD LAS BOLONHE-600G",
        "margem": 100,
        "tem_custo": false,
        "giro": 14,
        "receita": 349.86,
        "lucro": 349.86,
        "hora_pico": "5h",
        "classificacao": "volume",
        "cls_label": "📦 Alto giro"
      },
      {
        "nome": "HEREFORD",
        "margem": 100,
        "tem_custo": false,
        "giro": 5,
        "receita": 349.77,
        "lucro": 349.77,
        "hora_pico": "14h",
        "classificacao": "volume",
        "cls_label": "📦 Alto giro"
      },
      {
        "nome": "MONSTER ENERGY SEM AÇÚCARES",
        "margem": 100,
        "tem_custo": false,
        "giro": 25,
        "receita": 349.75,
        "lucro": 349.75,
        "hora_pico": "18h",
        "classificacao": "volume",
        "cls_label": "📦 Alto giro"
      },
      {
        "nome": "COCA-COLA REFRIGERANTE ZERO AÇÚCAR -350ML",
        "margem": 100,
        "tem_custo": false,
        "giro": 55,
        "receita": 329.45,
        "lucro": 329.45,
        "hora_pico": "20h",
        "classificacao": "volume",
        "cls_label": "📦 Alto giro"
      },
      {
        "nome": "RED BULL",
        "margem": 100,
        "tem_custo": false,
        "giro": 26,
        "receita": 324.74,
        "lucro": 324.74,
        "hora_pico": "9h",
        "classificacao": "volume",
        "cls_label": "📦 Alto giro"
      },
      {
        "nome": "OVOS MANT",
        "margem": 100,
        "tem_custo": false,
        "giro": 19,
        "receita": 322.81,
        "lucro": 322.81,
        "hora_pico": "18h",
        "classificacao": "volume",
        "cls_label": "📦 Alto giro"
      }
    ],
    "estoque_baixo": [],
    "instalacoes": {
      "soul_brooklin": {
        "nome": "Mercadinho 1",
        "faturamento": 31397.65,
        "transacoes": 3072
      },
      "minimart": {
        "nome": "Mercadinho 2",
        "faturamento": 1770.37,
        "transacoes": 212
      }
    }
  },
  "todas": {
    "faturamento": 81188.6,
    "faturamento_delta": 0,
    "ticket_medio": 10.15,
    "ticket_delta": 0,
    "transacoes": 8000,
    "transacoes_delta": 0,
    "margem_media": 0,
    "margem_delta": 0,
    "por_hora": [
      265,
      163,
      86,
      65,
      47,
      58,
      90,
      180,
      224,
      251,
      229,
      248,
      296,
      376,
      313,
      307,
      439,
      479,
      644,
      692,
      694,
      755,
      650,
      449
    ],
    "por_hora_soul": [
      253,
      133,
      76,
      64,
      43,
      54,
      87,
      166,
      207,
      234,
      211,
      222,
      272,
      346,
      278,
      273,
      398,
      449,
      617,
      662,
      654,
      709,
      607,
      416
    ],
    "por_hora_mini": [
      12,
      30,
      10,
      1,
      4,
      4,
      3,
      14,
      17,
      17,
      18,
      26,
      24,
      30,
      35,
      34,
      41,
      30,
      27,
      30,
      40,
      46,
      43,
      33
    ],
    "top_produtos": [
      {
        "nome": "FRESCOA ÁGUA MINERAL NATURAL SEM GÁS-1,5L",
        "vendas": 706,
        "receita": 4228.94,
        "margem": 0
      },
      {
        "nome": "HEINEKEN CERVEJA PURO MALTE COM ÁLCOOL-350ML",
        "vendas": 335,
        "receita": 2626.97,
        "margem": 0
      },
      {
        "nome": "COCA-COLA ZERO 600 ML",
        "vendas": 251,
        "receita": 2130.99,
        "margem": 0
      },
      {
        "nome": "CRYSTAL  ÁGUA MIN S GÁS-500ML",
        "vendas": 232,
        "receita": 925.68,
        "margem": 0
      },
      {
        "nome": "NESTLÉ CAFÉ TORRADO EM GRÃOS",
        "vendas": 228,
        "receita": 1821.72,
        "margem": 0
      },
      {
        "nome": "NESTLÉ BEBIDA CREMOSA",
        "vendas": 218,
        "receita": 2175.82,
        "margem": 0
      },
      {
        "nome": "CRYSTAL  ÁGUA MIN C GÁS-500ML",
        "vendas": 208,
        "receita": 829.92,
        "margem": 0
      },
      {
        "nome": "BUDWEISER CERVEJA 330ML",
        "vendas": 199,
        "receita": 1381.88,
        "margem": 0
      },
      {
        "nome": "STELLA ARTOIS PURE GOLD 330 ML",
        "vendas": 140,
        "receita": 1328.6,
        "margem": 0
      },
      {
        "nome": "COCA-COLA REFRIGERANTE ZERO AÇÚCAR -350ML",
        "vendas": 116,
        "receita": 694.24,
        "margem": 0
      }
    ],
    "analise_margem": [
      {
        "nome": "FRESCOA ÁGUA MINERAL NATURAL SEM GÁS-1,5L",
        "margem": 100,
        "tem_custo": false,
        "giro": 706,
        "receita": 4228.94,
        "lucro": 4228.94,
        "hora_pico": "21h",
        "classificacao": "volume",
        "cls_label": "📦 Alto giro"
      },
      {
        "nome": "HEINEKEN CERVEJA PURO MALTE COM ÁLCOOL-350ML",
        "margem": 100,
        "tem_custo": false,
        "giro": 335,
        "receita": 2626.97,
        "lucro": 2626.97,
        "hora_pico": "21h",
        "classificacao": "volume",
        "cls_label": "📦 Alto giro"
      },
      {
        "nome": "NESTLÉ BEBIDA CREMOSA",
        "margem": 100,
        "tem_custo": false,
        "giro": 218,
        "receita": 2175.82,
        "lucro": 2175.82,
        "hora_pico": "9h",
        "classificacao": "volume",
        "cls_label": "📦 Alto giro"
      },
      {
        "nome": "COCA-COLA ZERO 600 ML",
        "margem": 100,
        "tem_custo": false,
        "giro": 251,
        "receita": 2130.99,
        "lucro": 2130.99,
        "hora_pico": "20h",
        "classificacao": "volume",
        "cls_label": "📦 Alto giro"
      },
      {
        "nome": "NESTLÉ CAFÉ TORRADO EM GRÃOS",
        "margem": 100,
        "tem_custo": false,
        "giro": 228,
        "receita": 1821.72,
        "lucro": 1821.72,
        "hora_pico": "8h",
        "classificacao": "volume",
        "cls_label": "📦 Alto giro"
      },
      {
        "nome": "COCA-COLA REFRIGERANTE ZERO AÇÚCAR -2L",
        "margem": 100,
        "tem_custo": false,
        "giro": 96,
        "receita": 1434.45,
        "lucro": 1434.45,
        "hora_pico": "20h",
        "classificacao": "volume",
        "cls_label": "📦 Alto giro"
      },
      {
        "nome": "BUDWEISER CERVEJA 330ML",
        "margem": 100,
        "tem_custo": false,
        "giro": 199,
        "receita": 1381.88,
        "lucro": 1381.88,
        "hora_pico": "18h",
        "classificacao": "volume",
        "cls_label": "📦 Alto giro"
      },
      {
        "nome": "STELLA ARTOIS PURE GOLD 330 ML",
        "margem": 100,
        "tem_custo": false,
        "giro": 140,
        "receita": 1328.6,
        "lucro": 1328.6,
        "hora_pico": "22h",
        "classificacao": "volume",
        "cls_label": "📦 Alto giro"
      },
      {
        "nome": "LAYS SABOR SOUR",
        "margem": 100,
        "tem_custo": false,
        "giro": 80,
        "receita": 1119.2,
        "lucro": 1119.2,
        "hora_pico": "20h",
        "classificacao": "volume",
        "cls_label": "📦 Alto giro"
      },
      {
        "nome": "KIBON ESK SORV M BBOM 92,1G",
        "margem": 100,
        "tem_custo": false,
        "giro": 47,
        "receita": 1033.53,
        "lucro": 1033.53,
        "hora_pico": "19h",
        "classificacao": "volume",
        "cls_label": "📦 Alto giro"
      },
      {
        "nome": "CRYSTAL  ÁGUA MIN S GÁS-500ML",
        "margem": 100,
        "tem_custo": false,
        "giro": 232,
        "receita": 925.68,
        "lucro": 925.68,
        "hora_pico": "20h",
        "classificacao": "volume",
        "cls_label": "📦 Alto giro"
      },
      {
        "nome": "SANDUÍCHE BRIOCHE SALAME",
        "margem": 100,
        "tem_custo": false,
        "giro": 61,
        "receita": 853.39,
        "lucro": 853.39,
        "hora_pico": "20h",
        "classificacao": "volume",
        "cls_label": "📦 Alto giro"
      },
      {
        "nome": "MONSTER ENERGY SEM AÇÚCARES",
        "margem": 100,
        "tem_custo": false,
        "giro": 61,
        "receita": 853.39,
        "lucro": 853.39,
        "hora_pico": "9h",
        "classificacao": "volume",
        "cls_label": "📦 Alto giro"
      },
      {
        "nome": "BLUE MOON BELGIAN WHITE-350ML",
        "margem": 100,
        "tem_custo": false,
        "giro": 77,
        "receita": 846.23,
        "lucro": 846.23,
        "hora_pico": "18h",
        "classificacao": "volume",
        "cls_label": "📦 Alto giro"
      },
      {
        "nome": "CRYSTAL  ÁGUA MIN C GÁS-500ML",
        "margem": 100,
        "tem_custo": false,
        "giro": 208,
        "receita": 829.92,
        "lucro": 829.92,
        "hora_pico": "21h",
        "classificacao": "volume",
        "cls_label": "📦 Alto giro"
      },
      {
        "nome": "SAD LAS BOLONHE-600G",
        "margem": 100,
        "tem_custo": false,
        "giro": 32,
        "receita": 799.68,
        "lucro": 799.68,
        "hora_pico": "21h",
        "classificacao": "volume",
        "cls_label": "📦 Alto giro"
      },
      {
        "nome": "SANDUÍCHE CREMOSO FRANGO",
        "margem": 100,
        "tem_custo": false,
        "giro": 60,
        "receita": 779.4,
        "lucro": 779.4,
        "hora_pico": "16h",
        "classificacao": "volume",
        "cls_label": "📦 Alto giro"
      },
      {
        "nome": "PÃO DE LEITE",
        "margem": 100,
        "tem_custo": false,
        "giro": 57,
        "receita": 740.43,
        "lucro": 740.43,
        "hora_pico": "19h",
        "classificacao": "volume",
        "cls_label": "📦 Alto giro"
      },
      {
        "nome": "YOPRO BARRA MORANGO",
        "margem": 100,
        "tem_custo": false,
        "giro": 52,
        "receita": 727.48,
        "lucro": 727.48,
        "hora_pico": "16h",
        "classificacao": "volume",
        "cls_label": "📦 Alto giro"
      },
      {
        "nome": "NESTLE CHCO TRIO",
        "margem": 100,
        "tem_custo": false,
        "giro": 51,
        "receita": 713.49,
        "lucro": 713.49,
        "hora_pico": "22h",
        "classificacao": "volume",
        "cls_label": "📦 Alto giro"
      }
    ],
    "estoque_baixo": [],
    "instalacoes": {
      "soul_brooklin": {
        "nome": "Mercadinho 1",
        "faturamento": 76268.07,
        "transacoes": 7431
      },
      "minimart": {
        "nome": "Mercadinho 2",
        "faturamento": 4920.53,
        "transacoes": 569
      }
    }
  },
  "total_buscado": 8000,
  "produtos_com_custo": 0,
  "barcodes_mapeados": 0,
  "atualizado_em": "2026-06-18T20:31:06.309Z",
  "atualizado_brt": "2026-06-18 17:31"
}